{
  "projectKey": "EVERYTHING",
  "id": "Aa",
  "type": "step_based",
  "name": "a",
  "active": false,
  "versionTag": {
    "versionNumber": 1,
    "lastModifiedBy": {
      "login": "admin"
    },
    "lastModifiedOn": 1631635430946
  },
  "checklists": {
    "checklists": []
  },
  "delayedTriggersBehavior": {
    "delayWhileRunning": true,
    "squashDelayedTriggers": true,
    "suppressTriggersWhileRunning": true
  },
  "tags": [],
  "triggers": [
    {
      "id": "WFwFUOlQ",
      "type": "custom_python",
      "name": "Custom trigger",
      "delay": 3600,
      "active": true,
      "params": {
        "code": "import dataiku\nfrom dataiku.scenario import Trigger\nt \u003d Trigger()\nif True: # your condition here\n    t.fire()",
        "envSelection": {
          "envMode": "INHERIT"
        }
      },
      "graceDelaySettings": {
        "delay": 0,
        "checkAgainAfterGraceDelay": false
      }
    }
  ],
  "reporters": [],
  "params": {
    "steps": []
  },
  "automationLocal": false,
  "customFields": {}
}