{
  "type": "join",
  "neverRecomputeExistingPartitions": false,
  "optionalDependencies": false,
  "customMeta": {
    "kv": {}
  },
  "redispatchPartitioning": false,
  "maxRunningActivities": 0,
  "variables": {},
  "dkuProperties": [],
  "inputs": {
    "main": {
      "items": [
        {
          "ref": "aok",
          "deps": []
        },
        {
          "ref": "backend_2021_12_03_copy",
          "deps": []
        }
      ]
    }
  },
  "outputs": {
    "main": {
      "items": [
        {
          "ref": "aok_joined",
          "appendMode": false
        }
      ]
    }
  },
  "labels": [],
  "versionTag": {
    "versionNumber": 1,
    "lastModifiedBy": {
      "login": "admin"
    },
    "lastModifiedOn": 1645334728487
  },
  "creationTag": {
    "versionNumber": 0,
    "lastModifiedBy": {
      "login": "admin"
    },
    "lastModifiedOn": 1645334715531
  },
  "tags": [],
  "customFields": {},
  "checklists": {
    "checklists": []
  }
}